CHANGES.rst
MANIFEST.in
README.rst
buildout.cfg
setup.cfg
setup.py
pyramid_robot/__init__.py
pyramid_robot/layer.py
pyramid_robot.egg-info/PKG-INFO
pyramid_robot.egg-info/SOURCES.txt
pyramid_robot.egg-info/dependency_links.txt
pyramid_robot.egg-info/entry_points.txt
pyramid_robot.egg-info/not-zip-safe
pyramid_robot.egg-info/requires.txt
pyramid_robot.egg-info/top_level.txt
pyramid_robot/example/__init__.py
pyramid_robot/example/demoapp.py
pyramid_robot/tests/__init__.py
pyramid_robot/tests/test_robot.py
pyramid_robot/tests/robot/__init__.py
pyramid_robot/tests/robot/test_basic.robot
pyramid_robot/tests/robot/variables.py