Metadata-Version: 1.1
Name: pyramid-robot
Version: 1.1
Summary: Convenience package for enable RobotFramework tests under Pyramid.
Home-page: https://github.com/sneridagh/pyramid_robot
Author: Victor Fernandez de Alba
Author-email: sneridagh@gmail.com
License: UNKNOWN
Keywords: web pyramid pylons test robotframework robot selenium
Platform: UNKNOWN
Classifier: Programming Language :: Python
Classifier: Programming Language :: Python :: 2.7
Classifier: Programming Language :: Python :: 3.4
Classifier: Framework :: Pyramid
Classifier: Topic :: Internet :: WWW/HTTP
Classifier: Topic :: Internet :: WWW/HTTP :: WSGI :: Application
